<?xml version="1.0" encoding="utf-8"?>
<ModMetaData>
  <name>Standalone Hot Spring Mood Buff</name>
  <author>tyster</author>
  <packageId>tyster.StandaloneHotSpringMoodBuff</packageId>
  <supportedVersions>
    <li>1.6</li>
  </supportedVersions>
  <modVersion>1.0.0</modVersion>
  <description>adds vanilla hot spring mood buff to the standalone hot springs mod.</description>
  <modDependencies>
    <li>
      <packageId>balistafreak.standalonehotspring</packageId>
      <displayName>Standalone Hot Spring</displayName>
    </li>
  </modDependencies>
  <loadAfter>
    <li>balistafreak.standalonehotspring</li>
  </loadAfter>
  <loadBefore>
    <li>elindis.betterhotsprings</li>
  </loadBefore>
</ModMetaData>